[
    {
      "name": "Jordan",
      "code": "JO",
      "dial": "+962"
    },
    {
      "name": "Kuwait",
      "code": "KW",
      "dial": "+965"
    },
    {
      "name": "Lebanon",
      "code": "LB",
      "dial": "+961"
    },
    {
      "name": "Oman",
      "code": "OM",
      "dial": "+968"
    },
    {
      "name": "Qatar",
      "code": "QA",
      "dial": "+974"
    },
    {
      "name": "Saudi Arabia",
      "code": "SA",
      "dial": "+966"
    },
    {
      "name": "United Arab Emirates",
      "code": "AE",
      "dial": "+971"
    },
    {
      "name": "Madagascar",
      "code": "MG",
      "dial": "+261"
    }
]